{
	"name": "nova_structures:badlands_miner_outpost_mob",
	"fallback": "minecraft:empty",
	"elements": [
		{
			"weight": 1,
			"element": {
				"element_type": "minecraft:single_pool_element",
				"location": "nova_structures:badlands_miner_outpost/badlands_miner_outpost_mob_evoker",
				"projection": "rigid",
				"processors": "minecraft:empty"
			}
		},
		{
			"weight": 1,
			"element": {
				"element_type": "minecraft:single_pool_element",
				"location": "nova_structures:badlands_miner_outpost/badlands_miner_outpost_mob_pillager",
				"projection": "rigid",
				"processors": "minecraft:empty"
			}
		},
		{
			"weight": 1,
			"element": {
				"element_type": "minecraft:single_pool_element",
				"location": "nova_structures:badlands_miner_outpost/badlands_miner_outpost_mob_vindicator",
				"projection": "rigid",
				"processors": "minecraft:empty"
			}
		},
		{
			"weight": 1,
			"element": {
				"element_type": "minecraft:single_pool_element",
				"location": "nova_structures:badlands_miner_outpost/badlands_miner_outpost_mob_witch",
				"projection": "rigid",
				"processors": "minecraft:empty"
			}
		},
		{
			"weight": 2,
			"element": {
				"element_type": "minecraft:single_pool_element",
				"location": "nova_structures:badlands_miner_outpost/badlands_miner_outpost_mob_evoker_void",
				"projection": "rigid",
				"processors": "minecraft:empty"
			}
		},
		{
			"weight": 2,
			"element": {
				"element_type": "minecraft:single_pool_element",
				"location": "nova_structures:badlands_miner_outpost/badlands_miner_outpost_mob_pillager_void",
				"projection": "rigid",
				"processors": "minecraft:empty"
			}
		},
		{
			"weight": 2,
			"element": {
				"element_type": "minecraft:single_pool_element",
				"location": "nova_structures:badlands_miner_outpost/badlands_miner_outpost_mob_vindicator_void",
				"projection": "rigid",
				"processors": "minecraft:empty"
			}
		},
		{
			"weight": 2,
			"element": {
				"element_type": "minecraft:single_pool_element",
				"location": "nova_structures:badlands_miner_outpost/badlands_miner_outpost_mob_witch_void",
				"projection": "rigid",
				"processors": "minecraft:empty"
			}
		}
	]
}
