{
	"name": "nova_structures:bunker_enterance",
	"fallback": "minecraft:empty",
	"elements": [
		{
			"weight": 1,
			"element": {
				"element_type": "minecraft:single_pool_element",
				"location": "nova_structures:shrine/shrine_combat/elevator/shrine_elevator_start_1",
				"projection": "rigid",
				"processors": "minecraft:empty"
			}
		},
		{
			"weight": 1,
			"element": {
				"element_type": "minecraft:single_pool_element",
				"location": "nova_structures:shrine/shrine_combat/elevator/shrine_elevator_part1_1",
				"projection": "rigid",
				"processors": "minecraft:empty"
			}
		},
		{
			"weight": 1,
			"element": {
				"element_type": "minecraft:single_pool_element",
				"location": "nova_structures:shrine/shrine_combat/elevator/shrine_elevator_part2_1",
				"projection": "rigid",
				"processors": "minecraft:empty"
			}
		},
		{
			"weight": 1,
			"element": {
				"element_type": "minecraft:single_pool_element",
				"location": "nova_structures:shrine/shrine_combat/elevator/shrine_elevator_end_1",
				"projection": "rigid",
				"processors": "minecraft:empty"
			}
		},
		{
			"weight": 1,
			"element": {
				"element_type": "minecraft:single_pool_element",
				"location": "nova_structures:shrine/shrine_combat/room/shrine_goal_1",
				"projection": "rigid",
				"processors": "nova_structures:shrine_adabt"
			}
		},
		{
			"weight": 1,
			"element": {
				"element_type": "minecraft:single_pool_element",
				"location": "nova_structures:shrine/shrine_combat/room/room_frame_1_1",
				"projection": "rigid",
				"processors": "nova_structures:shrine_adabt"
			}
		}
	]
}
