{
	"name": "nova_structures:shrine/combat/shrine_vault",
	"fallback": "nova_structures:shrine/combat/shrine_vault",
	"elements": [
		{
			"weight": 1,
			"element": {
				"element_type": "minecraft:single_pool_element",
				"location": "nova_structures:shrine/shrine_combat/vault/shrine_vault_combat_1",
				"projection": "rigid",
				"processors": "minecraft:empty"
			}
		},
		{
			"weight": 1,
			"element": {
				"element_type": "minecraft:single_pool_element",
				"location": "nova_structures:shrine/shrine_combat/vault/shrine_vault_combat_2",
				"projection": "rigid",
				"processors": "minecraft:empty"
			}
		},
		{
			"weight": 1,
			"element": {
				"element_type": "minecraft:single_pool_element",
				"location": "nova_structures:shrine/shrine_combat/vault/shrine_vault_combat_3",
				"projection": "rigid",
				"processors": "minecraft:empty"
			}
		},
		{
			"weight": 1,
			"element": {
				"element_type": "minecraft:single_pool_element",
				"location": "nova_structures:shrine/shrine_combat/vault/shrine_vault_combat_4",
				"projection": "rigid",
				"processors": "minecraft:empty"
			}
		},
		{
			"weight": 1,
			"element": {
				"element_type": "minecraft:single_pool_element",
				"location": "nova_structures:shrine/shrine_combat/vault/shrine_vault_combat_5",
				"projection": "rigid",
				"processors": "minecraft:empty"
			}
		},
		{
			"weight": 1,
			"element": {
				"element_type": "minecraft:single_pool_element",
				"location": "nova_structures:shrine/shrine_combat/vault/shrine_vault_combat_ominous",
				"projection": "rigid",
				"processors": "minecraft:empty"
			}
		},
		{
			"weight": 2,
			"element": {
				"element_type": "minecraft:single_pool_element",
				"location": "nova_structures:shrine/shrine_combat/vault/shrine_vault_lesser",
				"projection": "rigid",
				"processors": "minecraft:empty"
			}
		},
		{
			"weight": 1,
			"element": {
				"element_type": "minecraft:single_pool_element",
				"location": "nova_structures:shrine/shrine_combat/vault/shrine_vault_lesser_ominous",
				"projection": "rigid",
				"processors": "minecraft:empty"
			}
		},
		{
			"weight": 9,
			"element": {
				"element_type": "minecraft:single_pool_element",
				"location": "nova_structures:shrine/shrine_combat/vault/shrine_vault_lesser_fail",
				"projection": "rigid",
				"processors": "minecraft:empty"
			}
		}
	]
}
